mirrorbox/__init__.py
mirrorbox/cache_handler.py
mirrorbox/cli.py
mirrorbox/compose_handler.py
mirrorbox/config_handler.py
mirrorbox/docker_cli.py
mirrorbox/gui_app.py
mirrorbox/help_formatter.py
mirrorbox/history_handler.py
mirrorbox/image_handler.py
mirrorbox/main.py
mirrorbox/mirrors.py
mirrorbox/dist/index.html
mirrorbox/dist/assets/index-C0LWqcUO.css
mirrorbox/dist/assets/index-D3ZaNYqz.js
mirrorbox/dist/assets/logo-9CR48aHW.png
mirrorbox-2.0.1.dist-info/licenses/LICENSE
mirrorbox-2.0.1.dist-info/METADATA
mirrorbox-2.0.1.dist-info/WHEEL
mirrorbox-2.0.1.dist-info/entry_points.txt
mirrorbox-2.0.1.dist-info/top_level.txt
mirrorbox-2.0.1.dist-info/RECORD
