Metadata-Version: 2.4
Name: mirrorbox
Version: 2.0.1
Summary: Enterprise Docker Mirror Client with AI-driven optimization and GUI.
Author-email: Pouya Rezapour <pouyarezapourr@gmail.com>
License: MIT License
Project-URL: Homepage, https://github.com/pouyarer/mirrorbox
Project-URL: Repository, https://github.com/pouyarer/mirrorbox
Classifier: Programming Language :: Python :: 3
Classifier: Operating System :: OS Independent
Classifier: Environment :: Console
Classifier: Topic :: System :: Networking
Requires-Python: >=3.10
License-File: LICENSE
Requires-Dist: typer>=0.9.0
Requires-Dist: rich>=13.0.0
Requires-Dist: requests>=2.28.0
Requires-Dist: pywebview>=5.0.0
Requires-Dist: platformdirs
Dynamic: license-file
